fabricawscfn/__init__.py
fabricawscfn/fabricawscfn.py
fabricawscfn-0.1.3.dist-info/LICENSE
fabricawscfn-0.1.3.dist-info/METADATA
fabricawscfn-0.1.3.dist-info/WHEEL
fabricawscfn-0.1.3.dist-info/top_level.txt
fabricawscfn-0.1.3.dist-info/RECORD
